{
  "entrypoints": [
    "main"
  ],
  "origins": {
    "1538": [
      867,
      1869,
      3249,
      3347,
      4813,
      6061,
      7643,
      8401,
      1538
    ],
    "2237": [
      2237
    ],
    "3347": [
      867,
      1538,
      1869,
      3249,
      4212,
      4813,
      7643,
      3347
    ],
    "17896441": [
      1538,
      1869,
      8401
    ],
    "59362658": [
      9325
    ],
    "main": [
      1869,
      5354,
      8792
    ],
    "runtime~main": [
      1869,
      8792,
      5354
    ],
    "0058b4c6": [
      849
    ],
    "01a85c17": [
      1869,
      8209
    ],
    "0e384e19": [
      3976
    ],
    "14eb3368": [
      1869,
      6969
    ],
    "18c41134": [
      9262
    ],
    "1dea6ca3": [
      5407
    ],
    "1e4232ab": [
      1953
    ],
    "1f391b9e": [
      1538,
      1869,
      6061
    ],
    "3217192f": [
      8462
    ],
    "33fc5bb8": [
      1538,
      1869,
      3347,
      867
    ],
    "36994c47": [
      9858
    ],
    "393be207": [
      4134
    ],
    "3a2db09e": [
      8121
    ],
    "533a09ca": [
      3098
    ],
    "5c868d36": [
      1974
    ],
    "5e90a9b3": [
      8025
    ],
    "5e95c892": [
      9647
    ],
    "621db11d": [
      1869,
      3347,
      4212
    ],
    "6875c492": [
      1538,
      1869,
      3347,
      4813
    ],
    "6bb166bd": [
      8518
    ],
    "7241b98a": [
      9155
    ],
    "73664a40": [
      1972
    ],
    "7661071f": [
      8737
    ],
    "814f3328": [
      7472
    ],
    "822bd8ab": [
      2748
    ],
    "8717b14a": [
      3694
    ],
    "925b3f96": [
      8609
    ],
    "9e4087bc": [
      2711
    ],
    "a6aa9e1f": [
      1538,
      1869,
      3347,
      7643
    ],
    "a7456010": [
      1235
    ],
    "a7bd4aaa": [
      7098
    ],
    "a94703ab": [
      1869,
      9048
    ],
    "aba21aa0": [
      5742
    ],
    "acecf23e": [
      1903
    ],
    "c15d9823": [
      8146
    ],
    "c4f5d8e4": [
      1869,
      2634
    ],
    "c8a4e95a": [
      845
    ],
    "c9c9bef8": [
      1794
    ],
    "ccc49370": [
      1538,
      1869,
      3347,
      3249
    ],
    "cfa0f765": [
      7145
    ],
    "d9f32620": [
      5557
    ],
    "df1a7709": [
      8868
    ],
    "dff1c289": [
      1724
    ],
    "e273c56f": [
      9328
    ],
    "e44a2883": [
      4736
    ],
    "e5aefb32": [
      3276
    ],
    "ef8b811a": [
      8947
    ],
    "f4f34a3a": [
      3637
    ],
    "f55d3e7a": [
      8863
    ],
    "f81c1134": [
      8130
    ],
    "f82cd581": [
      4584
    ],
    "styles": [
      867,
      1538,
      2634,
      3249,
      3347,
      4212,
      4813,
      5354,
      6061,
      6969,
      7643,
      8209,
      8401,
      8792,
      9048,
      1869
    ]
  },
  "assets": {
    "845": {
      "js": [
        {
          "file": "assets/js/c8a4e95a.6244a089.js",
          "hash": "cd61814f0365138f",
          "publicPath": "/assets/js/c8a4e95a.6244a089.js"
        }
      ]
    },
    "849": {
      "js": [
        {
          "file": "assets/js/0058b4c6.e054b0f9.js",
          "hash": "1997070412696eb3",
          "publicPath": "/assets/js/0058b4c6.e054b0f9.js"
        }
      ]
    },
    "867": {
      "js": [
        {
          "file": "assets/js/33fc5bb8.4a71e1ae.js",
          "hash": "86dd735ab707e257",
          "publicPath": "/assets/js/33fc5bb8.4a71e1ae.js"
        }
      ]
    },
    "1235": {
      "js": [
        {
          "file": "assets/js/a7456010.2f05987d.js",
          "hash": "60e554a4fd5cee17",
          "publicPath": "/assets/js/a7456010.2f05987d.js"
        }
      ]
    },
    "1538": {
      "js": [
        {
          "file": "assets/js/1538.2a6235f6.js",
          "hash": "91713b6cf6dc8bba",
          "publicPath": "/assets/js/1538.2a6235f6.js"
        }
      ]
    },
    "1724": {
      "js": [
        {
          "file": "assets/js/dff1c289.2a6f5631.js",
          "hash": "16941b2743a9e228",
          "publicPath": "/assets/js/dff1c289.2a6f5631.js"
        }
      ]
    },
    "1794": {
      "js": [
        {
          "file": "assets/js/c9c9bef8.64e2c9d0.js",
          "hash": "4bffbf357935f1a4",
          "publicPath": "/assets/js/c9c9bef8.64e2c9d0.js"
        }
      ]
    },
    "1869": {
      "css": [
        {
          "file": "assets/css/styles.8766fa05.css",
          "hash": "13d11ad6446c4bd1",
          "publicPath": "/assets/css/styles.8766fa05.css"
        }
      ]
    },
    "1903": {
      "js": [
        {
          "file": "assets/js/acecf23e.116cfa3d.js",
          "hash": "ccc40e352c88b81e",
          "publicPath": "/assets/js/acecf23e.116cfa3d.js"
        }
      ]
    },
    "1953": {
      "js": [
        {
          "file": "assets/js/1e4232ab.b66883bb.js",
          "hash": "ee8e6aa8c84f014d",
          "publicPath": "/assets/js/1e4232ab.b66883bb.js"
        }
      ]
    },
    "1972": {
      "js": [
        {
          "file": "assets/js/73664a40.109a10df.js",
          "hash": "9d340f14f326cc1f",
          "publicPath": "/assets/js/73664a40.109a10df.js"
        }
      ]
    },
    "1974": {
      "js": [
        {
          "file": "assets/js/5c868d36.53b5d755.js",
          "hash": "b253e20fc259d609",
          "publicPath": "/assets/js/5c868d36.53b5d755.js"
        }
      ]
    },
    "2237": {
      "js": [
        {
          "file": "assets/js/2237.81d21c10.js",
          "hash": "e92041f96f00ad07",
          "publicPath": "/assets/js/2237.81d21c10.js"
        }
      ]
    },
    "2634": {
      "js": [
        {
          "file": "assets/js/c4f5d8e4.4ee42dbc.js",
          "hash": "a094a35189c5b504",
          "publicPath": "/assets/js/c4f5d8e4.4ee42dbc.js"
        }
      ]
    },
    "2711": {
      "js": [
        {
          "file": "assets/js/9e4087bc.01f9a487.js",
          "hash": "99572f11a06da65c",
          "publicPath": "/assets/js/9e4087bc.01f9a487.js"
        }
      ]
    },
    "2748": {
      "js": [
        {
          "file": "assets/js/822bd8ab.d0b0d604.js",
          "hash": "a2080e646759417b",
          "publicPath": "/assets/js/822bd8ab.d0b0d604.js"
        }
      ]
    },
    "3098": {
      "js": [
        {
          "file": "assets/js/533a09ca.e67772d3.js",
          "hash": "dc120b4267db2d91",
          "publicPath": "/assets/js/533a09ca.e67772d3.js"
        }
      ]
    },
    "3249": {
      "js": [
        {
          "file": "assets/js/ccc49370.550cdc5f.js",
          "hash": "0648329041b26e41",
          "publicPath": "/assets/js/ccc49370.550cdc5f.js"
        }
      ]
    },
    "3276": {
      "js": [
        {
          "file": "assets/js/e5aefb32.4fc2b83c.js",
          "hash": "7c324d9156461d92",
          "publicPath": "/assets/js/e5aefb32.4fc2b83c.js"
        }
      ]
    },
    "3347": {
      "js": [
        {
          "file": "assets/js/3347.6e995e89.js",
          "hash": "d7415bb1003ed603",
          "publicPath": "/assets/js/3347.6e995e89.js"
        }
      ]
    },
    "3637": {
      "js": [
        {
          "file": "assets/js/f4f34a3a.0b0e8936.js",
          "hash": "8ca6a74174e921cc",
          "publicPath": "/assets/js/f4f34a3a.0b0e8936.js"
        }
      ]
    },
    "3694": {
      "js": [
        {
          "file": "assets/js/8717b14a.769a43d4.js",
          "hash": "dbd3324aca4c6cda",
          "publicPath": "/assets/js/8717b14a.769a43d4.js"
        }
      ]
    },
    "3976": {
      "js": [
        {
          "file": "assets/js/0e384e19.7a291f85.js",
          "hash": "215d6f3fd169d047",
          "publicPath": "/assets/js/0e384e19.7a291f85.js"
        }
      ]
    },
    "4134": {
      "js": [
        {
          "file": "assets/js/393be207.178a8206.js",
          "hash": "4a88fdde13cefcac",
          "publicPath": "/assets/js/393be207.178a8206.js"
        }
      ]
    },
    "4212": {
      "js": [
        {
          "file": "assets/js/621db11d.3e157b8d.js",
          "hash": "c1cc30d68b132496",
          "publicPath": "/assets/js/621db11d.3e157b8d.js"
        }
      ]
    },
    "4584": {
      "js": [
        {
          "file": "assets/js/f82cd581.a64723f0.js",
          "hash": "daf6532268958211",
          "publicPath": "/assets/js/f82cd581.a64723f0.js"
        }
      ]
    },
    "4736": {
      "js": [
        {
          "file": "assets/js/e44a2883.7be0e4df.js",
          "hash": "436e4221556cc312",
          "publicPath": "/assets/js/e44a2883.7be0e4df.js"
        }
      ]
    },
    "4813": {
      "js": [
        {
          "file": "assets/js/6875c492.f34884a9.js",
          "hash": "8bbed69a01dc9790",
          "publicPath": "/assets/js/6875c492.f34884a9.js"
        }
      ]
    },
    "5354": {
      "js": [
        {
          "file": "assets/js/runtime~main.5f9b0483.js",
          "hash": "2ff9c1bc338f734e",
          "publicPath": "/assets/js/runtime~main.5f9b0483.js"
        }
      ]
    },
    "5407": {
      "js": [
        {
          "file": "assets/js/1dea6ca3.d349707f.js",
          "hash": "bd5ec72e8315d334",
          "publicPath": "/assets/js/1dea6ca3.d349707f.js"
        }
      ]
    },
    "5557": {
      "js": [
        {
          "file": "assets/js/d9f32620.01f81fea.js",
          "hash": "5ff41d0ad6553a4c",
          "publicPath": "/assets/js/d9f32620.01f81fea.js"
        }
      ]
    },
    "5742": {
      "js": [
        {
          "file": "assets/js/aba21aa0.88370a23.js",
          "hash": "aaf47a8f2d5469fb",
          "publicPath": "/assets/js/aba21aa0.88370a23.js"
        }
      ]
    },
    "6061": {
      "js": [
        {
          "file": "assets/js/1f391b9e.83e71f57.js",
          "hash": "a8ea55fb4cefb4d8",
          "publicPath": "/assets/js/1f391b9e.83e71f57.js"
        }
      ]
    },
    "6969": {
      "js": [
        {
          "file": "assets/js/14eb3368.28622de9.js",
          "hash": "a065d76da0a0c1c2",
          "publicPath": "/assets/js/14eb3368.28622de9.js"
        }
      ]
    },
    "7098": {
      "js": [
        {
          "file": "assets/js/a7bd4aaa.19aaac9d.js",
          "hash": "4b132d86b3662286",
          "publicPath": "/assets/js/a7bd4aaa.19aaac9d.js"
        }
      ]
    },
    "7145": {
      "js": [
        {
          "file": "assets/js/cfa0f765.0b4edf36.js",
          "hash": "14f79420ce18ada8",
          "publicPath": "/assets/js/cfa0f765.0b4edf36.js"
        }
      ]
    },
    "7472": {
      "js": [
        {
          "file": "assets/js/814f3328.a6e8bc05.js",
          "hash": "fc7074e056b5bd98",
          "publicPath": "/assets/js/814f3328.a6e8bc05.js"
        }
      ]
    },
    "7643": {
      "js": [
        {
          "file": "assets/js/a6aa9e1f.4558fe1f.js",
          "hash": "9475a0b682fb0c71",
          "publicPath": "/assets/js/a6aa9e1f.4558fe1f.js"
        }
      ]
    },
    "8025": {
      "js": [
        {
          "file": "assets/js/5e90a9b3.88c7e6af.js",
          "hash": "affb634b30b5341d",
          "publicPath": "/assets/js/5e90a9b3.88c7e6af.js"
        }
      ]
    },
    "8121": {
      "js": [
        {
          "file": "assets/js/3a2db09e.47526f45.js",
          "hash": "6477db9982fe4ca2",
          "publicPath": "/assets/js/3a2db09e.47526f45.js"
        }
      ]
    },
    "8130": {
      "js": [
        {
          "file": "assets/js/f81c1134.c1804344.js",
          "hash": "ec5065bd5389d8dd",
          "publicPath": "/assets/js/f81c1134.c1804344.js"
        }
      ]
    },
    "8146": {
      "js": [
        {
          "file": "assets/js/c15d9823.3e568a8c.js",
          "hash": "6ed164e93d5ce934",
          "publicPath": "/assets/js/c15d9823.3e568a8c.js"
        }
      ]
    },
    "8209": {
      "js": [
        {
          "file": "assets/js/01a85c17.2e89b25c.js",
          "hash": "1bb1c094e1fe218f",
          "publicPath": "/assets/js/01a85c17.2e89b25c.js"
        }
      ]
    },
    "8401": {
      "js": [
        {
          "file": "assets/js/17896441.fad2fb2c.js",
          "hash": "b0a7d45b96fe20d3",
          "publicPath": "/assets/js/17896441.fad2fb2c.js"
        }
      ]
    },
    "8462": {
      "js": [
        {
          "file": "assets/js/3217192f.789420b0.js",
          "hash": "e72db2805975d833",
          "publicPath": "/assets/js/3217192f.789420b0.js"
        }
      ]
    },
    "8518": {
      "js": [
        {
          "file": "assets/js/6bb166bd.19372cdd.js",
          "hash": "3601b529236ef3a7",
          "publicPath": "/assets/js/6bb166bd.19372cdd.js"
        }
      ]
    },
    "8609": {
      "js": [
        {
          "file": "assets/js/925b3f96.0225871e.js",
          "hash": "eeb7aa9f3e6fbc44",
          "publicPath": "/assets/js/925b3f96.0225871e.js"
        }
      ]
    },
    "8737": {
      "js": [
        {
          "file": "assets/js/7661071f.eaf06871.js",
          "hash": "6e76451b8d13b024",
          "publicPath": "/assets/js/7661071f.eaf06871.js"
        }
      ]
    },
    "8792": {
      "js": [
        {
          "file": "assets/js/main.a3581484.js",
          "hash": "f621a529cc33a5f5",
          "publicPath": "/assets/js/main.a3581484.js"
        }
      ]
    },
    "8863": {
      "js": [
        {
          "file": "assets/js/f55d3e7a.0af1d2be.js",
          "hash": "47b5e9605d243084",
          "publicPath": "/assets/js/f55d3e7a.0af1d2be.js"
        }
      ]
    },
    "8868": {
      "js": [
        {
          "file": "assets/js/df1a7709.662e3dc6.js",
          "hash": "bc442f8fe4a9f6bc",
          "publicPath": "/assets/js/df1a7709.662e3dc6.js"
        }
      ]
    },
    "8947": {
      "js": [
        {
          "file": "assets/js/ef8b811a.19a6bbe5.js",
          "hash": "127124bc3d5a8c2f",
          "publicPath": "/assets/js/ef8b811a.19a6bbe5.js"
        }
      ]
    },
    "9048": {
      "js": [
        {
          "file": "assets/js/a94703ab.2178391f.js",
          "hash": "11f5bae36ca7e23f",
          "publicPath": "/assets/js/a94703ab.2178391f.js"
        }
      ]
    },
    "9155": {
      "js": [
        {
          "file": "assets/js/7241b98a.06bc15e6.js",
          "hash": "0d03a9dcf2255ead",
          "publicPath": "/assets/js/7241b98a.06bc15e6.js"
        }
      ]
    },
    "9262": {
      "js": [
        {
          "file": "assets/js/18c41134.ba613961.js",
          "hash": "f89ecf03a3d566be",
          "publicPath": "/assets/js/18c41134.ba613961.js"
        }
      ]
    },
    "9325": {
      "js": [
        {
          "file": "assets/js/59362658.ecb8778a.js",
          "hash": "6aefd50fb79337b6",
          "publicPath": "/assets/js/59362658.ecb8778a.js"
        }
      ]
    },
    "9328": {
      "js": [
        {
          "file": "assets/js/e273c56f.dc04a8c9.js",
          "hash": "21350ccc756bbdf9",
          "publicPath": "/assets/js/e273c56f.dc04a8c9.js"
        }
      ]
    },
    "9647": {
      "js": [
        {
          "file": "assets/js/5e95c892.4ed0b4b0.js",
          "hash": "19bbdca3f9f786e8",
          "publicPath": "/assets/js/5e95c892.4ed0b4b0.js"
        }
      ]
    },
    "9858": {
      "js": [
        {
          "file": "assets/js/36994c47.56f87c0d.js",
          "hash": "a76ad44da7a4f2b9",
          "publicPath": "/assets/js/36994c47.56f87c0d.js"
        }
      ]
    }
  }
}